[
  {
    "id": "vestas_v236_15mw",
    "name": "V236-15.0 MW",
    "manufacturer": "Vestas",
    "rated_power_kw": 15000,
    "rotor_diameter_m": 236,
    "hub_height_m": 125,
    "iec_class": "IA",
    "cut_in_speed": 3.0,
    "cut_out_speed": 25.0,
    "rated_speed": 11.0,
    "power_curve": [
      {"wind_speed": 0, "power": 0},
      {"wind_speed": 3, "power": 0},
      {"wind_speed": 4, "power": 160},
      {"wind_speed": 5, "power": 500},
      {"wind_speed": 6, "power": 1100},
      {"wind_speed": 7, "power": 2100},
      {"wind_speed": 8, "power": 3700},
      {"wind_speed": 9, "power": 5800},
      {"wind_speed": 10, "power": 8700},
      {"wind_speed": 11, "power": 12200},
      {"wind_speed": 12, "power": 14500},
      {"wind_speed": 13, "power": 15000},
      {"wind_speed": 14, "power": 15000},
      {"wind_speed": 25, "power": 15000},
      {"wind_speed": 25.1, "power": 0}
    ],
    "ct_curve": [
      {"wind_speed": 3, "power": 0.92},
      {"wind_speed": 5, "power": 0.86},
      {"wind_speed": 7, "power": 0.82},
      {"wind_speed": 9, "power": 0.78},
      {"wind_speed": 11, "power": 0.55},
      {"wind_speed": 13, "power": 0.38},
      {"wind_speed": 15, "power": 0.28},
      {"wind_speed": 20, "power": 0.20},
      {"wind_speed": 25, "power": 0.16}
    ]
  },
  {
    "id": "siemens_sg14_236dd",
    "name": "SG 14-236 DD",
    "manufacturer": "Siemens Gamesa",
    "rated_power_kw": 14000,
    "rotor_diameter_m": 236,
    "hub_height_m": 120,
    "iec_class": "IA",
    "cut_in_speed": 3.0,
    "cut_out_speed": 25.0,
    "rated_speed": 11.5,
    "power_curve": [
      {"wind_speed": 0, "power": 0},
      {"wind_speed": 3, "power": 0},
      {"wind_speed": 4, "power": 140},
      {"wind_speed": 5, "power": 450},
      {"wind_speed": 6, "power": 1000},
      {"wind_speed": 7, "power": 1900},
      {"wind_speed": 8, "power": 3400},
      {"wind_speed": 9, "power": 5400},
      {"wind_speed": 10, "power": 8000},
      {"wind_speed": 11, "power": 11500},
      {"wind_speed": 12, "power": 13500},
      {"wind_speed": 13, "power": 14000},
      {"wind_speed": 14, "power": 14000},
      {"wind_speed": 25, "power": 14000},
      {"wind_speed": 25.1, "power": 0}
    ],
    "ct_curve": [
      {"wind_speed": 3, "power": 0.90},
      {"wind_speed": 5, "power": 0.84},
      {"wind_speed": 7, "power": 0.80},
      {"wind_speed": 9, "power": 0.76},
      {"wind_speed": 11, "power": 0.52},
      {"wind_speed": 13, "power": 0.36},
      {"wind_speed": 15, "power": 0.26},
      {"wind_speed": 25, "power": 0.15}
    ]
  },
  {
    "id": "ge_haliade_x_14mw",
    "name": "Haliade-X 14 MW",
    "manufacturer": "GE Vernova",
    "rated_power_kw": 14000,
    "rotor_diameter_m": 220,
    "hub_height_m": 138,
    "iec_class": "IB",
    "cut_in_speed": 3.0,
    "cut_out_speed": 25.0,
    "rated_speed": 12.0,
    "power_curve": [
      {"wind_speed": 0, "power": 0},
      {"wind_speed": 3, "power": 0},
      {"wind_speed": 4, "power": 130},
      {"wind_speed": 5, "power": 420},
      {"wind_speed": 6, "power": 960},
      {"wind_speed": 7, "power": 1850},
      {"wind_speed": 8, "power": 3300},
      {"wind_speed": 9, "power": 5200},
      {"wind_speed": 10, "power": 7700},
      {"wind_speed": 11, "power": 10800},
      {"wind_speed": 12, "power": 13200},
      {"wind_speed": 13, "power": 14000},
      {"wind_speed": 14, "power": 14000},
      {"wind_speed": 25, "power": 14000},
      {"wind_speed": 25.1, "power": 0}
    ],
    "ct_curve": [
      {"wind_speed": 3, "power": 0.91},
      {"wind_speed": 5, "power": 0.85},
      {"wind_speed": 7, "power": 0.81},
      {"wind_speed": 9, "power": 0.77},
      {"wind_speed": 12, "power": 0.48},
      {"wind_speed": 15, "power": 0.27},
      {"wind_speed": 20, "power": 0.19},
      {"wind_speed": 25, "power": 0.15}
    ]
  },
  {
    "id": "vestas_v150_4200",
    "name": "V150-4.2 MW",
    "manufacturer": "Vestas",
    "rated_power_kw": 4200,
    "rotor_diameter_m": 150,
    "hub_height_m": 105,
    "iec_class": "IIA",
    "cut_in_speed": 3.0,
    "cut_out_speed": 25.0,
    "rated_speed": 13.0,
    "power_curve": [
      {"wind_speed": 0, "power": 0},
      {"wind_speed": 3, "power": 0},
      {"wind_speed": 4, "power": 60},
      {"wind_speed": 5, "power": 154},
      {"wind_speed": 6, "power": 310},
      {"wind_speed": 7, "power": 554},
      {"wind_speed": 8, "power": 900},
      {"wind_speed": 9, "power": 1370},
      {"wind_speed": 10, "power": 1960},
      {"wind_speed": 11, "power": 2680},
      {"wind_speed": 12, "power": 3400},
      {"wind_speed": 13, "power": 4000},
      {"wind_speed": 14, "power": 4150},
      {"wind_speed": 15, "power": 4200},
      {"wind_speed": 25, "power": 4200},
      {"wind_speed": 25.1, "power": 0}
    ],
    "ct_curve": [
      {"wind_speed": 3, "power": 0.90},
      {"wind_speed": 5, "power": 0.85},
      {"wind_speed": 8, "power": 0.80},
      {"wind_speed": 10, "power": 0.75},
      {"wind_speed": 12, "power": 0.55},
      {"wind_speed": 15, "power": 0.35},
      {"wind_speed": 20, "power": 0.20},
      {"wind_speed": 25, "power": 0.15}
    ]
  }
]
